LICENSE.txt
MANIFEST.in
README.txt
setup.py
lfc_theme/__init__.py
lfc_theme.egg-info/PKG-INFO
lfc_theme.egg-info/SOURCES.txt
lfc_theme.egg-info/dependency_links.txt
lfc_theme.egg-info/not-zip-safe
lfc_theme.egg-info/pbr.json
lfc_theme.egg-info/requires.txt
lfc_theme.egg-info/top_level.txt
lfc_theme/locale/de/LC_MESSAGES/django.mo
lfc_theme/locale/de/LC_MESSAGES/django.po
lfc_theme/locale/fr/LC_MESSAGES/django.mo
lfc_theme/locale/fr/LC_MESSAGES/django.po
lfc_theme/locale/pl/LC_MESSAGES/django.mo
lfc_theme/locale/pl/LC_MESSAGES/django.po
lfc_theme/static/.DS_Store
lfc_theme/static/lfc_theme/blueprint/ie.css
lfc_theme/static/lfc_theme/blueprint/print.css
lfc_theme/static/lfc_theme/blueprint/screen.css
lfc_theme/static/lfc_theme/blueprint/plugins/buttons/readme.txt
lfc_theme/static/lfc_theme/blueprint/plugins/buttons/screen.css
lfc_theme/static/lfc_theme/blueprint/plugins/buttons/icons/cross.png
lfc_theme/static/lfc_theme/blueprint/plugins/buttons/icons/key.png
lfc_theme/static/lfc_theme/blueprint/plugins/buttons/icons/tick.png
lfc_theme/static/lfc_theme/blueprint/plugins/fancy-type/readme.txt
lfc_theme/static/lfc_theme/blueprint/plugins/fancy-type/screen.css
lfc_theme/static/lfc_theme/blueprint/plugins/link-icons/readme.txt
lfc_theme/static/lfc_theme/blueprint/plugins/link-icons/screen.css
lfc_theme/static/lfc_theme/blueprint/plugins/link-icons/icons/doc.png
lfc_theme/static/lfc_theme/blueprint/plugins/link-icons/icons/email.png
lfc_theme/static/lfc_theme/blueprint/plugins/link-icons/icons/external.png
lfc_theme/static/lfc_theme/blueprint/plugins/link-icons/icons/feed.png
lfc_theme/static/lfc_theme/blueprint/plugins/link-icons/icons/im.png
lfc_theme/static/lfc_theme/blueprint/plugins/link-icons/icons/pdf.png
lfc_theme/static/lfc_theme/blueprint/plugins/link-icons/icons/visited.png
lfc_theme/static/lfc_theme/blueprint/plugins/link-icons/icons/xls.png
lfc_theme/static/lfc_theme/blueprint/plugins/rtl/readme.txt
lfc_theme/static/lfc_theme/blueprint/plugins/rtl/screen.css
lfc_theme/static/lfc_theme/blueprint/src/forms.css
lfc_theme/static/lfc_theme/blueprint/src/grid.css
lfc_theme/static/lfc_theme/blueprint/src/grid.png
lfc_theme/static/lfc_theme/blueprint/src/ie.css
